jeke_understat_scrapper-1.0.2.dist-info/licenses/LICENSE
understatapi/__init__.py
understatapi/api.py
understatapi/exceptions.py
understatapi/utils.py
understatapi/endpoints/__init__.py
understatapi/endpoints/base.py
understatapi/endpoints/league.py
understatapi/endpoints/match.py
understatapi/endpoints/player.py
understatapi/endpoints/team.py
understatapi/parsers/__init__.py
understatapi/parsers/base.py
understatapi/parsers/league.py
understatapi/parsers/match.py
understatapi/parsers/player.py
understatapi/parsers/team.py
jeke_understat_scrapper-1.0.2.dist-info/METADATA
jeke_understat_scrapper-1.0.2.dist-info/WHEEL
jeke_understat_scrapper-1.0.2.dist-info/top_level.txt
jeke_understat_scrapper-1.0.2.dist-info/RECORD
