Metadata-Version: 2.4
Name: jeke-understat-scrapper
Version: 1.0.2
Summary: A Python API for scraping football data from understat.com
Home-page: https://github.com/jeke-deportivas/jeke-understat-scrapper
Author: jeke-deportivas
Author-email: info@jekedeportivas.com
License: MIT
Project-URL: Source, https://github.com/jeke-deportivas/jeke-understat-scrapper
Project-URL: Download, https://pypi.org/project/jeke-understat-scrapper/#files
Keywords: statistics,xG,expected,goals,fpl,fantasy,premier,league,understat,football,web,scraping,scraper
Classifier: Development Status :: 5 - Production/Stable
Classifier: License :: OSI Approved :: MIT License
Classifier: Programming Language :: Python :: 3
Classifier: Programming Language :: Python :: 3.10
Classifier: Programming Language :: Python :: 3.11
Classifier: Programming Language :: Python :: 3.12
Classifier: Programming Language :: Python :: 3.13
Classifier: Topic :: Software Development :: Libraries :: Python Modules
Requires-Python: >=3.10
License-File: LICENSE
Requires-Dist: requests>=2.20.0
Dynamic: license-file
